AUTHORS
CHANGELOG.txt
DESCRIPTION
LICENSE
MANIFEST.in
README.rst
setup.py
django_feedback_form.egg-info/PKG-INFO
django_feedback_form.egg-info/SOURCES.txt
django_feedback_form.egg-info/dependency_links.txt
django_feedback_form.egg-info/requires.txt
django_feedback_form.egg-info/top_level.txt
feedback_form/__init__.py
feedback_form/admin.py
feedback_form/app_settings.py
feedback_form/forms.py
feedback_form/models.py
feedback_form/urls.py
feedback_form/views.py
feedback_form/migrations/0001_initial.py
feedback_form/migrations/__init__.py
feedback_form/south_migrations/0001_initial.py
feedback_form/south_migrations/0002_auto__add_field_feedback_content_type__add_field_feedback_object_id.py
feedback_form/south_migrations/0003_auto__chg_field_feedback_current_url.py
feedback_form/south_migrations/__init__.py
feedback_form/static/feedback_form/css/feedback_form.css
feedback_form/static/feedback_form/img/feedback.png
feedback_form/static/feedback_form/img/feedback_mobile.png
feedback_form/static/feedback_form/js/feedback_form.js
feedback_form/templates/feedback_form/feedback_form.html
feedback_form/templates/feedback_form/email/body.html
feedback_form/templates/feedback_form/email/confirmation_body.html
feedback_form/templates/feedback_form/email/confirmation_subject.html
feedback_form/templates/feedback_form/email/subject.html
feedback_form/templates/feedback_form/partials/form.html
feedback_form/templates/feedback_form/partials/form_content.html
feedback_form/templatetags/__init__.py
feedback_form/templatetags/feedback_tags.py
feedback_form/tests/__init__.py
feedback_form/tests/base_settings.py
feedback_form/tests/forms_tests.py
feedback_form/tests/models_tests.py
feedback_form/tests/settings.py
feedback_form/tests/tags_tests.py
feedback_form/tests/test_settings.py
feedback_form/tests/urls.py
feedback_form/tests/views_tests.py
feedback_form/tests/test_app/__init__.py
feedback_form/tests/test_app/models.py
feedback_form/tests/test_app/templates/404.html
feedback_form/tests/test_app/templates/base.html