Metadata-Version: 1.0
Name: django-feedback-form
Version: 1.3
Summary: Minified JQuery & Ajax feedback form to handle fast customer requests in Django
Home-page: https://github.com/bitmazk/django-feedback-form
Author: Tobias Lorenz
Author-email: tobias.lorenz@bitmazk.com
License: The MIT License
Keywords: django,feedback,form,contact
Platform: OS Independent
